pset4/src/base_modules/comp3.v
module comp3(
    input [2:0] a,
    input [2:0] b,
    output eq
);
    wire x0, x1, x2;
    xnor2$ xn0(.out(x0), .in0(a[0]), .in1(b[0]));
    xnor2$ xn1(.out(x1), .in1(a[1]), .in0(b[1])); // swapped pins ok
    xnor2$ xn2(.out(x2), .in0(a[2]), .in1(b[2]));
    
    wire x01;
    and2$ a0(.out(x01), .in0(x0), .in1(x1));
    and2$ a1(.out(eq),  .in0(x01), .in1(x2));
endmodule

pset4/testbench/comp3_tb.v
`timescale 1ns / 1ps

module comp3_tb;

    // 1. Inputs
    reg [2:0] a;
    reg [2:0] b;

    // 2. Outputs
    wire eq;

    // 3. Instantiate UUT
    comp3 uut (
        .a(a), 
        .b(b), 
        .eq(eq)
    );

    integer i, j;
    integer errors;

    // 4. Test Logic
    initial begin
        $dumpfile("comp3.vcd");
        $dumpvars(0, comp3_tb);

        a = 0; b = 0;
        errors = 0;

        $display("---------------------------------------------------");
        $display("Starting 3-bit Comparator Test...");
        $display("---------------------------------------------------");

        // Loop through ALL possible values for A (0-7) and B (0-7)
        for (i = 0; i < 8; i = i + 1) begin
            for (j = 0; j < 8; j = j + 1) begin
                
                a = i[2:0];
                b = j[2:0];
                
                #1; // Wait for logic

                // Check Logic: 
                // If i == j, eq must be 1.
                // If i != j, eq must be 0.
                if ( (i == j && eq !== 1) || (i !== j && eq !== 0) ) begin
                    $display("[FAIL] A=%b (%0d), B=%b (%0d). Got Eq=%b", a, i, b, j, eq);
                    errors = errors + 1;
                end 
            end
        end

        // --- Summary ---
        $display("---------------------------------------------------");
        if (errors == 0) $display("ALL TESTS PASSED: Checked all 64 combinations.");
        else $display("TEST FAILED: Found %0d errors.", errors);
        $display("---------------------------------------------------");
        $finish;
    end

endmodule

pset4/comp3.vcd
$date
	Mon Feb 16 23:29:06 2026
$end

$version
	Synopsys VCS version T-2022.06_Full64
$end

$timescale
	1ps
$end

$comment Csum: 1 8d840677028ccbef $end


$scope module comp3_tb $end
$var reg 3 ! a [2:0] $end
$var reg 3 " b [2:0] $end
$var wire 1 # eq $end
$var integer 32 $ i $end
$var integer 32 % j $end
$var integer 32 & errors $end

$scope module uut $end
$var wire 3 ' a [2:0] $end
$var wire 3 ( b [2:0] $end
$var wire 1 # eq $end
$var wire 1 ) x0 $end
$var wire 1 * x1 $end
$var wire 1 + x2 $end
$var wire 1 , x01 $end

$scope module xn0 $end
$var wire 1 - in0 $end
$var wire 1 . in1 $end
$var wire 1 / out $end
$upscope $end


$scope module xn1 $end
$var wire 1 0 in0 $end
$var wire 1 1 in1 $end
$var wire 1 2 out $end
$upscope $end


$scope module xn2 $end
$var wire 1 3 in0 $end
$var wire 1 4 in1 $end
$var wire 1 5 out $end
$upscope $end


$scope module a0 $end
$var wire 1 ) in0 $end
$var wire 1 * in1 $end
$var wire 1 6 out $end
$upscope $end


$scope module a1 $end
$var wire 1 , in0 $end
$var wire 1 + in1 $end
$var wire 1 7 out $end
$upscope $end

$upscope $end

$upscope $end

$enddefinitions $end

#0
$dumpvars
x6
x7
x#
0-
0.
x/
x)
x,
x*
x+
00
01
x2
03
04
x5
b000 !
b000 "
b00000000000000000000000000000000 &
b00000000000000000000000000000000 $
b00000000000000000000000000000000 %
b000 '
b000 (
$end
#250
1/
1)
12
1*
15
1+
#600
16
1,
#950
17
1#
#1000
b00000000000000000000000000000001 %
b001 "
b001 (
1.
#1250
0/
0)
#1600
06
0,
#1950
07
0#
#2000
b00000000000000000000000000000010 %
b010 "
b010 (
10
0.
#2250
1/
1)
02
0*
#3000
b00000000000000000000000000000011 %
b011 "
b011 (
1.
#3250
0/
0)
#4000
b00000000000000000000000000000100 %
b100 "
b100 (
14
00
0.
#4250
1/
1)
12
1*
05
0+
#4600
16
1,
#5000
b00000000000000000000000000000101 %
b101 "
b101 (
1.
#5250
0/
0)
#5600
06
0,
#6000
b00000000000000000000000000000110 %
b110 "
b110 (
10
0.
#6250
1/
1)
02
0*
#7000
b00000000000000000000000000000111 %
b111 "
b111 (
1.
#7250
0/
0)
#8000
b00000000000000000000000000001000 %
b00000000000000000000000000000001 $
b00000000000000000000000000000000 %
b001 !
b001 '
1-
b000 "
b000 (
04
00
0.
#8250
12
1*
15
1+
#9000
b00000000000000000000000000000001 %
b001 "
b001 (
1.
#9250
1/
1)
#9600
16
1,
#9950
17
1#
#10000
b00000000000000000000000000000010 %
b010 "
b010 (
10
0.
#10250
0/
0)
02
0*
#10600
06
0,
#10950
07
0#
#11000
b00000000000000000000000000000011 %
b011 "
b011 (
1.
#11250
1/
1)
#12000
b00000000000000000000000000000100 %
b100 "
b100 (
14
00
0.
#12250
0/
0)
12
1*
05
0+
#13000
b00000000000000000000000000000101 %
b101 "
b101 (
1.
#13250
1/
1)
#13600
16
1,
#14000
b00000000000000000000000000000110 %
b110 "
b110 (
10
0.
#14250
0/
0)
02
0*
#14600
06
0,
#15000
b00000000000000000000000000000111 %
b111 "
b111 (
1.
#15250
1/
1)
#16000
b00000000000000000000000000001000 %
b00000000000000000000000000000010 $
b00000000000000000000000000000000 %
b010 !
b010 '
11
0-
b000 "
b000 (
04
00
0.
#16250
15
1+
#17000
b00000000000000000000000000000001 %
b001 "
b001 (
1.
#17250
0/
0)
#18000
b00000000000000000000000000000010 %
b010 "
b010 (
10
0.
#18250
1/
1)
12
1*
#18600
16
1,
#18950
17
1#
#19000
b00000000000000000000000000000011 %
b011 "
b011 (
1.
#19250
0/
0)
#19600
06
0,
#19950
07
0#
#20000
b00000000000000000000000000000100 %
b100 "
b100 (
14
00
0.
#20250
1/
1)
02
0*
05
0+
#21000
b00000000000000000000000000000101 %
b101 "
b101 (
1.
#21250
0/
0)
#22000
b00000000000000000000000000000110 %
b110 "
b110 (
10
0.
#22250
1/
1)
12
1*
#22600
16
1,
#23000
b00000000000000000000000000000111 %
b111 "
b111 (
1.
#23250
0/
0)
#23600
06
0,
#24000
b00000000000000000000000000001000 %
b00000000000000000000000000000011 $
b00000000000000000000000000000000 %
b011 !
b011 '
1-
b000 "
b000 (
04
00
0.
#24250
02
0*
15
1+
#25000
b00000000000000000000000000000001 %
b001 "
b001 (
1.
#25250
1/
1)
#26000
b00000000000000000000000000000010 %
b010 "
b010 (
10
0.
#26250
0/
0)
12
1*
#27000
b00000000000000000000000000000011 %
b011 "
b011 (
1.
#27250
1/
1)
#27600
16
1,
#27950
17
1#
#28000
b00000000000000000000000000000100 %
b100 "
b100 (
14
00
0.
#28250
0/
0)
02
0*
05
0+
#28600
07
0#
06
0,
#29000
b00000000000000000000000000000101 %
b101 "
b101 (
1.
#29250
1/
1)
#30000
b00000000000000000000000000000110 %
b110 "
b110 (
10
0.
#30250
0/
0)
12
1*
#31000
b00000000000000000000000000000111 %
b111 "
b111 (
1.
#31250
1/
1)
#31600
16
1,
#32000
b00000000000000000000000000001000 %
b00000000000000000000000000000100 $
b00000000000000000000000000000000 %
b100 !
b100 '
13
01
0-
b000 "
b000 (
04
00
0.
#33000
b00000000000000000000000000000001 %
b001 "
b001 (
1.
#33250
0/
0)
#33600
06
0,
#34000
b00000000000000000000000000000010 %
b010 "
b010 (
10
0.
#34250
1/
1)
02
0*
#35000
b00000000000000000000000000000011 %
b011 "
b011 (
1.
#35250
0/
0)
#36000
b00000000000000000000000000000100 %
b100 "
b100 (
14
00
0.
#36250
1/
1)
12
1*
15
1+
#36600
16
1,
#36950
17
1#
#37000
b00000000000000000000000000000101 %
b101 "
b101 (
1.
#37250
0/
0)
#37600
06
0,
#37950
07
0#
#38000
b00000000000000000000000000000110 %
b110 "
b110 (
10
0.
#38250
1/
1)
02
0*
#39000
b00000000000000000000000000000111 %
b111 "
b111 (
1.
#39250
0/
0)
#40000
b00000000000000000000000000001000 %
b00000000000000000000000000000101 $
b00000000000000000000000000000000 %
b101 !
b101 '
1-
b000 "
b000 (
04
00
0.
#40250
12
1*
05
0+
#41000
b00000000000000000000000000000001 %
b001 "
b001 (
1.
#41250
1/
1)
#41600
16
1,
#42000
b00000000000000000000000000000010 %
b010 "
b010 (
10
0.
#42250
0/
0)
02
0*
#42600
06
0,
#43000
b00000000000000000000000000000011 %
b011 "
b011 (
1.
#43250
1/
1)
#44000
b00000000000000000000000000000100 %
b100 "
b100 (
14
00
0.
#44250
0/
0)
12
1*
15
1+
#45000
b00000000000000000000000000000101 %
b101 "
b101 (
1.
#45250
1/
1)
#45600
16
1,
#45950
17
1#
#46000
b00000000000000000000000000000110 %
b110 "
b110 (
10
0.
#46250
0/
0)
02
0*
#46600
06
0,
#46950
07
0#
#47000
b00000000000000000000000000000111 %
b111 "
b111 (
1.
#47250
1/
1)
#48000
b00000000000000000000000000001000 %
b00000000000000000000000000000110 $
b00000000000000000000000000000000 %
b110 !
b110 '
11
0-
b000 "
b000 (
04
00
0.
#48250
05
0+
#49000
b00000000000000000000000000000001 %
b001 "
b001 (
1.
#49250
0/
0)
#50000
b00000000000000000000000000000010 %
b010 "
b010 (
10
0.
#50250
1/
1)
12
1*
#50600
16
1,
#51000
b00000000000000000000000000000011 %
b011 "
b011 (
1.
#51250
0/
0)
#51600
06
0,
#52000
b00000000000000000000000000000100 %
b100 "
b100 (
14
00
0.
#52250
1/
1)
02
0*
15
1+
#53000
b00000000000000000000000000000101 %
b101 "
b101 (
1.
#53250
0/
0)
#54000
b00000000000000000000000000000110 %
b110 "
b110 (
10
0.
#54250
1/
1)
12
1*
#54600
16
1,
#54950
17
1#
#55000
b00000000000000000000000000000111 %
b111 "
b111 (
1.
#55250
0/
0)
#55600
06
0,
#55950
07
0#
#56000
b00000000000000000000000000001000 %
b00000000000000000000000000000111 $
b00000000000000000000000000000000 %
b111 !
b111 '
1-
b000 "
b000 (
04
00
0.
#56250
02
0*
05
0+
#57000
b00000000000000000000000000000001 %
b001 "
b001 (
1.
#57250
1/
1)
#58000
b00000000000000000000000000000010 %
b010 "
b010 (
10
0.
#58250
0/
0)
12
1*
#59000
b00000000000000000000000000000011 %
b011 "
b011 (
1.
#59250
1/
1)
#59600
16
1,
#60000
b00000000000000000000000000000100 %
b100 "
b100 (
14
00
0.
#60250
0/
0)
02
0*
15
1+
#60600
17
1#
06
0,
#60950
07
0#
#61000
b00000000000000000000000000000101 %
b101 "
b101 (
1.
#61250
1/
1)
#62000
b00000000000000000000000000000110 %
b110 "
b110 (
10
0.
#62250
0/
0)
12
1*
#63000
b00000000000000000000000000000111 %
b111 "
b111 (
1.
#63250
1/
1)
#63600
16
1,
#63950
17
1#
#64000
b00000000000000000000000000001000 %
b00000000000000000000000000001000 $
