pset4/src/base_modules/comp3.v
// Simplified comp3.v
module comp3(
    input [2:0] a,
    input [2:0] b,
    output eq
);
    wire x0, x1, x2;
    xnor2$ xn0(.out(x0), .in0(a[0]), .in1(b[0]));
    xnor2$ xn1(.out(x1), .in0(a[1]), .in1(b[1]));
    xnor2$ xn2(.out(x2), .in0(a[2]), .in1(b[2]));
    
    wire x01;
    and2$ a0(.out(x01), .in0(x0), .in1(x1));
    and2$ a1(.out(eq),  .in0(x01), .in1(x2)); // Direct match output
endmodule

pset4/src/control_flow/dependency_logic.v
module dependency_logic(
    input wire [2:0] E_dst_idx,
    input wire [2:0] M_dst_idx,
    input wire [2:0] WB_dst_idx,
    input wire [2:0] D_src1_idx,
    input wire [2:0] D_src2_idx,
    output wire D_stall
);

    // 1. Compare D_src1 against all future destinations
    wire match1_E, match1_M, match1_WB;
    comp3 c1e (.eq(match1_E),  .a(D_src1_idx), .b(E_dst_idx));
    comp3 c1m (.eq(match1_M),  .a(D_src1_idx), .b(M_dst_idx));
    comp3 c1w (.eq(match1_WB), .a(D_src1_idx), .b(WB_dst_idx));

    // 2. Compare D_src2 against all future destinations
    wire match2_E, match2_M, match2_WB;
    comp3 c2e (.eq(match2_E),  .a(D_src2_idx), .b(E_dst_idx));
    comp3 c2m (.eq(match2_M),  .a(D_src2_idx), .b(M_dst_idx));
    comp3 c2w (.eq(match2_WB), .a(D_src2_idx), .b(WB_dst_idx));

    // 3. Combine matches (OR Tree)
    // If ANY match is true, we must stall.
    
    // Combine Src1 Hazards
    wire stall_src1_temp, stall_src1;
    or2$ o1 (.out(stall_src1_temp), .in0(match1_E), .in1(match1_M));
    or2$ o2 (.out(stall_src1),      .in0(stall_src1_temp), .in1(match1_WB));

    // Combine Src2 Hazards
    wire stall_src2_temp, stall_src2;
    or2$ o3 (.out(stall_src2_temp), .in0(match2_E), .in1(match2_M));
    or2$ o4 (.out(stall_src2),      .in0(stall_src2_temp), .in1(match2_WB));

    // Final Stall Output (Src1 Hazard OR Src2 Hazard)
    or2$ o_final (.out(D_stall), .in0(stall_src1), .in1(stall_src2));

endmodule

pset4/testbench/dependency_logic_tb.v
`timescale 1ns / 1ps

module dependency_logic_tb;

    // 1. Inputs
    reg [2:0] E_dst_idx;
    reg [2:0] M_dst_idx;
    reg [2:0] WB_dst_idx;
    reg [2:0] D_src1_idx;
    reg [2:0] D_src2_idx;

    // 2. Outputs
    wire D_stall;

    // 3. Instantiate UUT
    dependency_logic uut (
        .E_dst_idx(E_dst_idx),
        .M_dst_idx(M_dst_idx),
        .WB_dst_idx(WB_dst_idx),
        .D_src1_idx(D_src1_idx),
        .D_src2_idx(D_src2_idx),
        .D_stall(D_stall)
    );

    integer errors;

    // 4. Test Logic
    initial begin
        $dumpfile("dependency_logic.vcd");
        $dumpvars(0, dependency_logic_tb);

        // Init
        E_dst_idx = 0; M_dst_idx = 0; WB_dst_idx = 0;
        D_src1_idx = 1; D_src2_idx = 2; // Set sources to something distinct
        errors = 0;

        $display("---------------------------------------------------");
        $display("Starting Dependency Logic Test...");
        $display("---------------------------------------------------");

        // --- TEST 1: No Hazards ---
        // Destinations (4,5,6) are different from Sources (1,2)
        E_dst_idx = 3'd4; M_dst_idx = 3'd5; WB_dst_idx = 3'd6;
        D_src1_idx = 3'd1; D_src2_idx = 3'd2;
        #5;
        check_stall(0, "No Hazards");


        // --- TEST 2: Execute Hazard (Src1) ---
        // E_dst (1) == D_src1 (1) -> STALL
        E_dst_idx = 3'd1;
        #5;
        check_stall(1, "Execute Hazard (Src1)");
        E_dst_idx = 3'd4; // Reset


        // --- TEST 3: Memory Hazard (Src1) ---
        // M_dst (1) == D_src1 (1) -> STALL
        M_dst_idx = 3'd1;
        #5;
        check_stall(1, "Memory Hazard (Src1)");
        M_dst_idx = 3'd5; // Reset


        // --- TEST 4: Writeback Hazard (Src2) ---
        // WB_dst (2) == D_src2 (2) -> STALL
        WB_dst_idx = 3'd2;
        #5;
        check_stall(1, "WB Hazard (Src2)");
        WB_dst_idx = 3'd6; // Reset


        // --- TEST 5: Multiple Hazards ---
        // E_dst matches Src1 AND M_dst matches Src2 -> STALL
        E_dst_idx = 3'd1; 
        M_dst_idx = 3'd2;
        #5;
        check_stall(1, "Double Hazard");


        // --- Summary ---
        $display("---------------------------------------------------");
        if (errors == 0) $display("ALL TESTS PASSED: Logic Correct.");
        else $display("TEST FAILED: Found %0d errors.", errors);
        $display("---------------------------------------------------");
        $finish;
    end

    // Helper Task
    task check_stall;
        input exp_stall;
        input [8*30:1] test_name;
        begin
            if (D_stall !== exp_stall) begin
                $display("[FAIL] %s: Exp Stall=%b, Got %b", test_name, exp_stall, D_stall);
                $display("       Src1=%d, Src2=%d | E_dst=%d, M_dst=%d, WB_dst=%d", 
                        D_src1_idx, D_src2_idx, E_dst_idx, M_dst_idx, WB_dst_idx);
                errors = errors + 1;
            end else begin
                $display("[PASS] %s", test_name);
            end
        end
    endtask

endmodule

pset4/dependency_logic.vcd
$date
	Tue Feb 17 00:26:16 2026
$end

$version
	Synopsys VCS version T-2022.06_Full64
$end

$timescale
	1ps
$end

$comment Csum: 1 edb6ef217d589586 $end


$scope module dependency_logic_tb $end
$var reg 3 ! E_dst_idx [2:0] $end
$var reg 3 " M_dst_idx [2:0] $end
$var reg 3 # WB_dst_idx [2:0] $end
$var reg 3 $ D_src1_idx [2:0] $end
$var reg 3 % D_src2_idx [2:0] $end
$var wire 1 & D_stall $end
$var integer 32 ' errors $end

$scope task check_stall $end
$var reg 1 ( exp_stall $end
$var reg 240 ) test_name [240:1] $end
$upscope $end


$scope module uut $end
$var wire 3 * E_dst_idx [2:0] $end
$var wire 3 + M_dst_idx [2:0] $end
$var wire 3 , WB_dst_idx [2:0] $end
$var wire 3 - D_src1_idx [2:0] $end
$var wire 3 . D_src2_idx [2:0] $end
$var wire 1 & D_stall $end
$var wire 1 / match1_E $end
$var wire 1 0 match1_M $end
$var wire 1 1 match1_WB $end
$var wire 1 2 match2_E $end
$var wire 1 3 match2_M $end
$var wire 1 4 match2_WB $end
$var wire 1 5 stall_src1_temp $end
$var wire 1 6 stall_src1 $end
$var wire 1 7 stall_src2_temp $end
$var wire 1 8 stall_src2 $end

$scope module c1e $end
$var wire 3 - a [2:0] $end
$var wire 3 * b [2:0] $end
$var wire 1 / eq $end
$var wire 1 9 x0 $end
$var wire 1 : x1 $end
$var wire 1 ; x2 $end
$var wire 1 < x01 $end

$scope module xn0 $end
$var wire 1 = in0 $end
$var wire 1 > in1 $end
$var wire 1 ? out $end
$upscope $end


$scope module xn1 $end
$var wire 1 @ in0 $end
$var wire 1 A in1 $end
$var wire 1 B out $end
$upscope $end


$scope module xn2 $end
$var wire 1 C in0 $end
$var wire 1 D in1 $end
$var wire 1 E out $end
$upscope $end


$scope module a0 $end
$var wire 1 9 in0 $end
$var wire 1 : in1 $end
$var wire 1 F out $end
$upscope $end


$scope module a1 $end
$var wire 1 < in0 $end
$var wire 1 ; in1 $end
$var wire 1 G out $end
$upscope $end

$upscope $end


$scope module c1m $end
$var wire 3 - a [2:0] $end
$var wire 3 + b [2:0] $end
$var wire 1 0 eq $end
$var wire 1 H x0 $end
$var wire 1 I x1 $end
$var wire 1 J x2 $end
$var wire 1 K x01 $end

$scope module xn0 $end
$var wire 1 L in0 $end
$var wire 1 M in1 $end
$var wire 1 N out $end
$upscope $end


$scope module xn1 $end
$var wire 1 O in0 $end
$var wire 1 P in1 $end
$var wire 1 Q out $end
$upscope $end


$scope module xn2 $end
$var wire 1 R in0 $end
$var wire 1 S in1 $end
$var wire 1 T out $end
$upscope $end


$scope module a0 $end
$var wire 1 H in0 $end
$var wire 1 I in1 $end
$var wire 1 U out $end
$upscope $end


$scope module a1 $end
$var wire 1 K in0 $end
$var wire 1 J in1 $end
$var wire 1 V out $end
$upscope $end

$upscope $end


$scope module c1w $end
$var wire 3 - a [2:0] $end
$var wire 3 , b [2:0] $end
$var wire 1 1 eq $end
$var wire 1 W x0 $end
$var wire 1 X x1 $end
$var wire 1 Y x2 $end
$var wire 1 Z x01 $end

$scope module xn0 $end
$var wire 1 [ in0 $end
$var wire 1 \ in1 $end
$var wire 1 ] out $end
$upscope $end


$scope module xn1 $end
$var wire 1 ^ in0 $end
$var wire 1 _ in1 $end
$var wire 1 ` out $end
$upscope $end


$scope module xn2 $end
$var wire 1 a in0 $end
$var wire 1 b in1 $end
$var wire 1 c out $end
$upscope $end


$scope module a0 $end
$var wire 1 W in0 $end
$var wire 1 X in1 $end
$var wire 1 d out $end
$upscope $end


$scope module a1 $end
$var wire 1 Z in0 $end
$var wire 1 Y in1 $end
$var wire 1 e out $end
$upscope $end

$upscope $end


$scope module c2e $end
$var wire 3 . a [2:0] $end
$var wire 3 * b [2:0] $end
$var wire 1 2 eq $end
$var wire 1 f x0 $end
$var wire 1 g x1 $end
$var wire 1 h x2 $end
$var wire 1 i x01 $end

$scope module xn0 $end
$var wire 1 j in0 $end
$var wire 1 k in1 $end
$var wire 1 l out $end
$upscope $end


$scope module xn1 $end
$var wire 1 m in0 $end
$var wire 1 n in1 $end
$var wire 1 o out $end
$upscope $end


$scope module xn2 $end
$var wire 1 p in0 $end
$var wire 1 q in1 $end
$var wire 1 r out $end
$upscope $end


$scope module a0 $end
$var wire 1 f in0 $end
$var wire 1 g in1 $end
$var wire 1 s out $end
$upscope $end


$scope module a1 $end
$var wire 1 i in0 $end
$var wire 1 h in1 $end
$var wire 1 t out $end
$upscope $end

$upscope $end


$scope module c2m $end
$var wire 3 . a [2:0] $end
$var wire 3 + b [2:0] $end
$var wire 1 3 eq $end
$var wire 1 u x0 $end
$var wire 1 v x1 $end
$var wire 1 w x2 $end
$var wire 1 x x01 $end

$scope module xn0 $end
$var wire 1 y in0 $end
$var wire 1 z in1 $end
$var wire 1 { out $end
$upscope $end


$scope module xn1 $end
$var wire 1 | in0 $end
$var wire 1 } in1 $end
$var wire 1 ~ out $end
$upscope $end


$scope module xn2 $end
$var wire 1 "! in0 $end
$var wire 1 "" in1 $end
$var wire 1 "# out $end
$upscope $end


$scope module a0 $end
$var wire 1 u in0 $end
$var wire 1 v in1 $end
$var wire 1 "$ out $end
$upscope $end


$scope module a1 $end
$var wire 1 x in0 $end
$var wire 1 w in1 $end
$var wire 1 "% out $end
$upscope $end

$upscope $end


$scope module c2w $end
$var wire 3 . a [2:0] $end
$var wire 3 , b [2:0] $end
$var wire 1 4 eq $end
$var wire 1 "& x0 $end
$var wire 1 "' x1 $end
$var wire 1 "( x2 $end
$var wire 1 ") x01 $end

$scope module xn0 $end
$var wire 1 "* in0 $end
$var wire 1 "+ in1 $end
$var wire 1 ", out $end
$upscope $end


$scope module xn1 $end
$var wire 1 "- in0 $end
$var wire 1 ". in1 $end
$var wire 1 "/ out $end
$upscope $end


$scope module xn2 $end
$var wire 1 "0 in0 $end
$var wire 1 "1 in1 $end
$var wire 1 "2 out $end
$upscope $end


$scope module a0 $end
$var wire 1 "& in0 $end
$var wire 1 "' in1 $end
$var wire 1 "3 out $end
$upscope $end


$scope module a1 $end
$var wire 1 ") in0 $end
$var wire 1 "( in1 $end
$var wire 1 "4 out $end
$upscope $end

$upscope $end


$scope module o1 $end
$var wire 1 / in0 $end
$var wire 1 0 in1 $end
$var wire 1 "5 out $end
$upscope $end


$scope module o2 $end
$var wire 1 5 in0 $end
$var wire 1 1 in1 $end
$var wire 1 "6 out $end
$upscope $end


$scope module o3 $end
$var wire 1 2 in0 $end
$var wire 1 3 in1 $end
$var wire 1 "7 out $end
$upscope $end


$scope module o4 $end
$var wire 1 7 in0 $end
$var wire 1 4 in1 $end
$var wire 1 "8 out $end
$upscope $end


$scope module o_final $end
$var wire 1 6 in0 $end
$var wire 1 8 in1 $end
$var wire 1 "9 out $end
$upscope $end

$upscope $end

$upscope $end

$enddefinitions $end

#0
$dumpvars
x&
x(
x"6
x"7
x"8
x"9
x"5
x6
x5
x8
x7
b001 $
b010 %
b100 !
b101 "
b110 #
bxxxxxxxxxxxxxxxxxxxxxxxxxxxxxxxxxxxxxxxxxxxxxxxxxxxxxxxxxxxxxxxxxxxxxxxxxxxxxxxxxxxxxxxxxxxxxxxxxxxxxxxxxxxxxxxxxxxxxxxxxxxxxxxxxxxxxxxxxxxxxxxxxxxxxxxxxxxxxxxxxxxxxxxxxxxxxxxxxxxxxxxxxxxxxxxxxxxxxxxxxxxxxxxxxxxxxxxxxxxxxxxxxxxxxxxxxxxxxxxx )
b00000000000000000000000000000000 '
xF
1=
0>
x?
x9
x<
x:
x;
0@
0A
xB
0C
1D
xE
xU
1L
1M
xN
xH
xK
xI
xJ
0O
0P
xQ
0R
1S
xT
xd
1[
0\
x]
xW
xZ
xX
xY
1^
0_
x`
0a
1b
xc
xs
0j
0k
xl
xf
xi
xg
xh
0m
1n
xo
0p
1q
xr
x"$
0y
1z
x{
xu
xx
xv
xw
0|
1}
x~
0"!
1""
x"#
x"3
0"*
0"+
x",
x"&
x")
x"'
x"(
1"-
1".
x"/
0"0
1"1
x"2
xG
x/
xV
x0
xe
x1
xt
x2
x"%
x3
x"4
x4
b001 -
b100 *
b101 +
b110 ,
b010 .
$end
#250
0"2
0"(
0"#
0w
0r
0h
1"/
1"'
0~
0v
0o
0g
1",
1"&
0{
0u
1l
1f
0c
0Y
0T
0J
0E
0;
0`
0X
1Q
1I
1B
1:
0]
0W
1N
1H
0?
09
#600
0F
0<
1U
1K
0d
0Z
0G
0/
0V
00
0e
01
1"3
1")
0s
0i
0"$
0x
0t
02
0"%
03
0"4
04
#950
0"7
07
0"5
05
#1300
0"6
06
0"8
08
#1650
0"9
0&
#5000
0(
b000000000000000000000000000000000000000000000000000000000000000000000000000000000000000000000000000000000000000000000000000000000000000000000000000000000000000001001110011011110010000001001000011000010111101001100001011100100110010001110011 )
b001 !
b001 *
1>
1k
0D
0q
#5250
1r
1h
1E
1;
0l
0f
1?
19
#5600
1F
1<
#5950
1G
1/
#6300
1"5
15
#6650
1"6
16
#7000
1"9
1&
#10000
1(
b000000000000000000000000000000000000000000000000000000000000000000000000010001010111100001100101011000110111010101110100011001010010000001001000011000010111101001100001011100100110010000100000001010000101001101110010011000110011000100101001 )
b100 !
b100 *
0>
0k
1D
1q
b001 "
b001 +
0S
0""
#10250
1"#
1w
1T
1J
0r
0h
0E
0;
1l
1f
0?
09
#10600
0F
0<
0G
0/
1V
10
#15000
b000000000000000000000000000000000000000000000000000000000000000000000000000000000100110101100101011011010110111101110010011110010010000001001000011000010111101001100001011100100110010000100000001010000101001101110010011000110011000100101001 )
b101 "
b101 +
1S
1""
b010 #
b010 ,
0b
0"1
#15250
1"2
1"(
1c
1Y
0"#
0w
0T
0J
#15600
0V
00
1"4
14
#15950
1"8
18
0"5
05
#16300
0"6
06
#20000
b000000000000000000000000000000000000000000000000000000000000000000000000000000000000000000000000000000000000000001010111010000100010000001001000011000010111101001100001011100100110010000100000001010000101001101110010011000110011001000101001 )
b110 #
b110 ,
1b
1"1
b001 !
b001 *
1>
1k
0D
0q
b010 "
b010 +
0M
0z
1O
1|
0S
0""
#20250
1"#
1w
1T
1J
1~
1v
0Q
0I
1{
1u
0N
0H
1r
1h
1E
1;
0l
0f
1?
19
0"2
0"(
0c
0Y
#20600
0"4
04
1F
1<
1"$
1x
0U
0K
1V
10
#20950
1"5
15
0V
00
1"%
13
1G
1/
0"8
08
#21300
0"9
0&
1"7
17
1"6
16
#21650
1"9
1&
1"8
18
#25000
b000000000000000000000000000000000000000000000000000000000000000000000000000000000000000000000000000000000000000000000000000000000000000001000100011011110111010101100010011011000110010100100000010010000110000101111010011000010111001001100100 )
